MANIFEST.in
README.rst
TITLE.txt
lh-agpl3-LICENSE.txt
setup.py
./bin/bearerTokenProc.py
./bin/mmwsBaseManage.py
./bin/opScnPetstore.py
./bin/rinvoker.py
./bin/rinvokerPetstore.py
./bin/wsInvokerIcmExamples.py
unisos2/__init__.py
unisos2.mmwsIcm.egg-info/PKG-INFO
unisos2.mmwsIcm.egg-info/SOURCES.txt
unisos2.mmwsIcm.egg-info/dependency_links.txt
unisos2.mmwsIcm.egg-info/namespace_packages.txt
unisos2.mmwsIcm.egg-info/not-zip-safe
unisos2.mmwsIcm.egg-info/requires.txt
unisos2.mmwsIcm.egg-info/top_level.txt
unisos2/mmwsIcm/__init__.py
unisos2/mmwsIcm/bearerToken.py
unisos2/mmwsIcm/mmwsBases.py
unisos2/mmwsIcm/mmwsIcmPkgThis.py
unisos2/mmwsIcm/ro.py
unisos2/mmwsIcm/wsInvokerIcm.py
unisos2/mmwsIcm-base/__init__.py
unisos2/mmwsIcm-base/opScn-1.py
unisos2/mmwsIcm-base/opScnCommon.py